pyoperaciones/NumerosPrimos.py
pyoperaciones/untitled0.py
NumerosPrimosV1-0.1.dist-info/LICENSE.txt
NumerosPrimosV1-0.1.dist-info/METADATA
NumerosPrimosV1-0.1.dist-info/WHEEL
NumerosPrimosV1-0.1.dist-info/top_level.txt
NumerosPrimosV1-0.1.dist-info/RECORD
